<Action id="43053" issue="29396" author="esplinr" type="comment" created="2018-04-17 13:27:54.0" updateauthor="esplinr" updated="2018-04-17 13:27:54.0"> <body><! CDATA This issue requires us to reproducing it before we can investigate it further, but this sprint our team is focused on the next release. We'll add this to the planning for the sprint starting on April 25.  If someone else could reproduce and investigate this issue, it will increase our ability to deal with it in the next sprint.  ></body> </Action>
<Action id="43055" issue="29396" author="vladimirwork" type="comment" body="FYI  ~sergey.minaev   ~Artemkaaas   ~ozheregelya   ~zhigunenko.dsr " created="2018-04-17 13:42:30.0" updateauthor="vladimirwork" updated="2018-04-17 13:42:30.0"/>
<Action id="43056" issue="29396" author="sergey.minaev" type="comment" body=" ~krw910   ~VladimirWork   ~esplinr  this issue is not actual for latest master with Revocation changes." created="2018-04-17 13:50:12.0" updateauthor="sergey.minaev" updated="2018-04-17 13:50:12.0"/>
<Action id="44650" issue="29396" author="esplinr" type="comment" created="2018-05-18 12:25:24.0" updateauthor="esplinr" updated="2018-05-18 12:25:24.0"> <body><! CDATA Our changes in the 1.4 release for wallet storage changed the way the nonce is stored. Because we changed the way that a nonce is added to the wallet, this issue is no longer applicable.  Thanks for the issue report.  ></body> </Action>
