<Action id="55449" issue="36535" author="scottz" type="comment" body="Instead of using a feature-specific test epic like this one, the release mgmt team prefers that any new testtasks should be added to development epic (in this case, FAB-6135). Or add automated regression tests to one of the existing system test category epics." created="2019-01-09 17:44:24.0" updateauthor="scottz" updated="2019-01-09 17:44:24.0"/>
<Action id="55655" issue="36535" author="kchristidis" type="comment" created="2019-01-14 23:07:36.0" updateauthor="kchristidis" updated="2019-01-14 23:07:36.0"> <body><! CDATA Example of an item that should be common across all tests and needs to be recorded here:  Logging for everything orderer-related should be set to DEBUG level. The only exception is {{orderer.common.cluster.step}}. (Thanks Yacov.)  ></body> </Action>
<Action id="55656" issue="36535" author="kchristidis" type="comment" created="2019-01-14 23:10:52.0" updateauthor="kchristidis" updated="2019-01-18 22:47:42.0"> <body><! CDATA Cross-posting  ~suryalnvs 's comment:  *Environment*: * IKS (3 worker nodes - Each node with 4CPU && 16 GB RAM)  *Fabric network*: * 3 orderers, 2 organizations with 2 peers each are distributed across 3 workers nodes and running as each individual pod. Orderer and peer Data is persisted to IBM Cloud block storage and uses {{amd64-2.0.0-stable}} images from nexus.  *Configuration*: * Environment variables for the orderer processes:  https://hastebin.com/rodewawuli.cs  * {{configx.yaml}}:  https://hastebin.com/texozupite.coffeescript   ></body> </Action>
<Action id="56733" issue="36535" author="kchristidis" type="comment" body=" ~suryalnvs ,  ~scottz : Are the environment variables and configuration settings still current? If not, can we provide the updated list?" created="2019-02-06 21:46:10.0" updateauthor="kchristidis" updated="2019-02-06 21:46:10.0"/>
<Action id="56817" issue="36535" author="scottz" type="comment" created="2019-02-08 21:50:51.0" updateauthor="scottz" updated="2019-02-08 21:50:51.0"> <body><! CDATA Updated our tests default settings in these files: * environment variables for orderers:  https://hastebin.com/rebunugama.cs   * configtx.yaml:  https://hastebin.com/qupizomeyu.coffeescript |https://hastebin.com/qupizomeyu.coffeescript      ></body> </Action>
<Action id="57006" issue="36535" author="scottz" type="comment" body="Updated configtx.yaml to accomodate new format for SnapshotInterval to use 100 MB instead of 500 transactions. https://hastebin.com/egehezuqux.coffeescript" created="2019-02-13 20:45:14.0" updateauthor="scottz" updated="2019-02-13 20:45:14.0"/>
<Action id="57009" issue="36535" author="kchristidis" type="comment" body="Thanks for making sure these are up-to-date!" created="2019-02-13 22:15:44.0" updateauthor="kchristidis" updated="2019-02-13 22:15:44.0"/>
<Action id="57088" issue="36535" author="scottz" type="comment" created="2019-02-16 00:49:30.0" updateauthor="scottz" updated="2019-02-16 00:49:30.0"> <body><! CDATA New recommendations for logging levels for most tests: INFO for everything, except two: {quote}FABRIC_LOGGING_SPEC=info:orderer.consensus.etcdraft=debug:orderer.common.cluster=debug {quote} Whereas for longruns and performance runs, use INFO (unless trying to reproduce issues to gather data).  ></body> </Action>
