<Action id="54018" issue="33490" author="kchristidis" type="comment" created="2018-11-29 16:47:56.0" updateauthor="kchristidis" updated="2018-11-29 16:48:30.0"> <body><! CDATA  ~guoger ,  ~adarshsaraf123 : What are your thoughts on labeling this story as help-wanted and issuing out a call for interested parties to contribute? (I am talking about the "unassigned" tasks.)  At a quick glance, it looks like this a set of tasks that can be managed with somewhat moderate guidance from our part. I might be underestimating the difficulty involved though. LMK what you think.  ></body> </Action>
<Action id="54019" issue="33490" author="guoger" type="comment" created="2018-11-29 17:20:03.0" updateauthor="guoger" updated="2018-11-29 17:20:03.0"> <body><! CDATA  ~kchristidis  I'm planning to take care of FAB-12998 once current CR stack settles. FAB-12709 needs special care as that switch would cause many UT to fail.  Other than these two, this story can be marked help-wanted safely IMO. Good idea!  ></body> </Action>
<Action id="54048" issue="33490" author="adarshsaraf123" type="comment" body=" ~kchristidis  Agreed." created="2018-11-30 06:30:13.0" updateauthor="adarshsaraf123" updated="2018-11-30 06:30:13.0"/>
<Action id="55943" issue="33490" author="kchristidis" type="comment" created="2019-01-21 18:11:10.0" updateauthor="kchristidis" updated="2019-01-21 18:11:10.0"> <body><! CDATA I'll be adding here a few bugs that should be backlogged.  https://jira.hyperledger.org/browse/FAB-13779  ></body> </Action>
