<Action id="59811" issue="39695" author="bharadwajambati1" type="comment" body=" https://gerrit.hyperledger.org/r/#/c/31263/ " created="2019-05-07 16:45:38.0" updateauthor="bharadwajambati1" updated="2019-05-07 16:45:38.0"/>
<Action id="59825" issue="39695" author="vijaypunugubati" type="comment" created="2019-05-07 22:28:34.0" updateauthor="vijaypunugubati" updated="2019-05-07 22:28:34.0"> <body><! CDATA This CR disable the chaincode-to-chaincode tests failing in Behave test while using chaincode example04 and chaincode_ex05 on different channels.   https://gerrit.hyperledger.org/r/#/c/31273/    ></body> </Action>
<Action id="60080" issue="39695" author="bharadwajambati1" type="comment" created="2019-05-16 17:46:55.0" updateauthor="bharadwajambati1" updated="2019-05-16 17:47:01.0"> <body><! CDATA Enabled tests related to chaincode path. It's the fix for the above comment   https://gerrit.hyperledger.org/r/#/c/31389/   ></body> </Action>
<Action id="62240" issue="39695" author="vijaypunugubati" type="comment" created="2019-07-30 00:55:06.0" updateauthor="vijaypunugubati" updated="2019-07-30 00:55:06.0"> <body><! CDATA *FAB-3888 :* Refer to Gossip tests and release system test, so this test case can be ignored.  *FAB-6256 :* Covered by new test-case FAB-15894 .  *FAB-5791 :* These behave tests are for older chaincode shim. The fabric/core/chaincode/shim/ contains tests for current shim.  *FAB-4703 :* This test is incorporated in integration/e2e/lifecycle/interop_test.go  *+FAB-5663 ,+ FAB-4717:* This test is referred to new task FAB-15903 which covers the test case.  *FAB-5663 :* This just tests the chaincode_ex05 function as it handles args (chan arg empty string / default to use value for current same chan), and so we can skip this.     All the errors on the above test scenarios are addressed.   ></body> </Action>
