<Action id="43368" issue="29591" author="lehors" type="comment" created="2018-04-24 17:18:41.0" updateauthor="lehors" updated="2018-04-24 17:19:57.0"> <body><! CDATA I just tried this on my Ubuntu 16.04.1 system and I couldn't reproduce the problem. Here is the peer I have:   Version: 1.1.0  Go version: go1.9.2  OS/Arch: linux/amd64  Experimental features: false  Chaincode:   Base Image Version: 0.4.6   Base Docker Namespace: hyperledger   Base Docker Label: org.hyperledger.fabric   Docker Namespace: hyperledger     ></body> </Action>
<Action id="43374" issue="29591" author="tboloo" type="comment" created="2018-04-24 19:09:21.0" updateauthor="tboloo" updated="2018-04-24 19:09:21.0"> <body><! CDATA Tried it on the different machine, same result: 1.1.0 fails with the expiration error as in FAB-8595, 1.1.0-preview fails with invalid memory address or nil pointer dereference.  Docker version 18.03.0-ce, build 0520e24  Debian GNU/Linux 9.4 (stretch)        ></body> </Action>
<Action id="43384" issue="29591" author="tboloo" type="comment" body="Update: works for version 1.0.6" created="2018-04-25 05:25:32.0" updateauthor="tboloo" updated="2018-04-25 05:25:32.0"/>
<Action id="43624" issue="29591" author="mastersingh24" type="comment" created="2018-04-29 09:11:07.0" updateauthor="mastersingh24" updated="2018-04-29 09:11:07.0"> <body><! CDATA  ~tboloo  - Which version of the fabric-samples are you running?  Can you make sure that you are running the v1.1.0 version of the samples?   {quote}git clone https://github.com/hyperledger/fabric-samples cd fabric-samples git checkout *v1.1.0*{quote}   ></body> </Action>
<Action id="44289" issue="29591" author="mastersingh24" type="comment" body="reducing this to medium for now and will close if we don&apos;t hear back from  ~tboloo  soon" created="2018-05-13 10:25:21.0" updateauthor="mastersingh24" updated="2018-05-13 10:25:21.0"/>
<Action id="44366" issue="29591" author="tboloo" type="comment" body="I did download the 1.1 release as  ~mastersingh24  suggested and I was not able to reproduce the issue." created="2018-05-14 20:13:27.0" updateauthor="tboloo" updated="2018-05-14 20:13:27.0"/>
