<IssueLink id="15037" linktype="10100" source="19361" destination="17971" sequence="0"/>
<IssueLink id="15038" linktype="10100" source="19361" destination="17972" sequence="1"/>
<IssueLink id="15039" linktype="10100" source="19361" destination="17986" sequence="2"/>
<IssueLink id="15040" linktype="10100" source="19361" destination="17987" sequence="3"/>
<IssueLink id="15041" linktype="10100" source="19361" destination="17988" sequence="4"/>
<IssueLink id="15042" linktype="10100" source="19361" destination="17989" sequence="5"/>
<IssueLink id="15043" linktype="10100" source="19361" destination="17990" sequence="6"/>
<IssueLink id="15044" linktype="10100" source="19361" destination="17991" sequence="7"/>
<IssueLink id="15045" linktype="10100" source="19361" destination="17992" sequence="8"/>
<IssueLink id="15046" linktype="10100" source="19361" destination="17993" sequence="9"/>
<IssueLink id="15048" linktype="10100" source="19361" destination="17995" sequence="10"/>
<IssueLink id="15049" linktype="10100" source="19361" destination="17996" sequence="11"/>
