<IssueLink id="22127" linktype="10003" source="28305" destination="16240"/>
<IssueLink id="22186" linktype="10200" source="28305" destination="28411"/>
<IssueLink id="22432" linktype="10200" source="28305" destination="28715"/>
<IssueLink id="22433" linktype="10200" source="28305" destination="28716"/>
<IssueLink id="22434" linktype="10200" source="28305" destination="28717"/>
<IssueLink id="22435" linktype="10200" source="28305" destination="28718"/>
<IssueLink id="22679" linktype="10200" source="28305" destination="21731"/>
<IssueLink id="22985" linktype="10200" source="28305" destination="29608"/>
<IssueLink id="23255" linktype="10200" source="28305" destination="29935"/>
<IssueLink id="23257" linktype="10200" source="28305" destination="29937"/>
<IssueLink id="24011" linktype="10200" source="28305" destination="30513"/>
<IssueLink id="24012" linktype="10200" source="28305" destination="30514"/>
