<Action id="64221" issue="40605" author="vladimirwork" type="comment" created="2019-10-01 10:46:57.0" updateauthor="vladimirwork" updated="2019-10-01 10:53:00.0"> <body><! CDATA Build Info: indy-node 1.10.0~dev1094  Steps to Reproduce: 1. Run load test without fees and tokens with forced VCs (1800 seconds).  Actual Results: Pool performed 10 VCs in 30 minutes after the first one.  ev@evernymr33:logs/2146_pbft_no_tokens_forced_vc.tar.gz ev@evernymr33:logs/performance_results_pbft_forced_01_10_2019.tar.gz  ></body> </Action>
<Action id="64222" issue="40605" author="vladimirwork" type="comment" created="2019-10-01 11:50:37.0" updateauthor="vladimirwork" updated="2019-10-01 11:50:37.0"> <body><! CDATA Build Info: indy-node 1.10.0~dev1094  Steps to Reproduce: 1. Stop primary (and ensure that primary has changed). 2. Start ex-primary and demote backup primary (and ensure that primary has changed). 3. Promote demoted node (and ensure that primary has changed).  https://github.com/hyperledger/indy-test-automation/blob/f3c0c75e04f416a81f22025146bc5ca9b1e2f718/system/indy-node-tests/TestAuditSuite.py#L153  Actual Results: Primary didn't change in Step 3 (but before PBFT this test passed).  ^audit_vc_issue_01_10_2019.tar.gz    ></body> </Action>
<Action id="64223" issue="40605" author="vladimirwork" type="comment" body="FYI  ~ashcherbakov   ~sergey.khoroshavin   ~anikitinDSR   ~Toktar " created="2019-10-01 11:51:42.0" updateauthor="vladimirwork" updated="2019-10-01 11:51:42.0"/>
<Action id="64274" issue="40605" author="vladimirwork" type="comment" created="2019-10-02 20:52:07.0" updateauthor="vladimirwork" updated="2019-10-02 20:52:07.0"> <body><! CDATA Build Info: indy-node 1.10.0~dev1094  Steps to Reproduce: 1. Run load test (5 txns/sec load rate) with forced VCs (1800) and debug logs. 2. Run load test (10 txns/sec load rate) with forced VCs (1800) and debug logs.  Actual Results: There are too many VCs during both load tests (30 actual against 6 expected for the last case for example).  ev@evernymr33:logs/pbft_5_per_sec_debug.tar.gz ev@evernymr33:logs/pbft_10_per_sec_debug.tar.gz  ></body> </Action>
<Action id="64485" issue="40605" author="vladimirwork" type="comment" created="2019-10-09 12:12:25.0" updateauthor="vladimirwork" updated="2019-10-09 12:12:25.0"> <body><! CDATA Build Info: indy-node 1.11.0~dev1101 plugins 1.0.4~dev102  Steps to Reproduce: 1. Run production load test (with tokens and fees) with forced VCs (1800).  Actual Results: Pool sustained the load for 8+ hours but we have an issue with 2 and 3 VCs in a row. !Figure1.png|thumbnail!  !Figure25.png|thumbnail!  ev@evernymr33:logs/pbft_forced_vc_08_10_2019.tar.gz  ></body> </Action>
<Action id="64560" issue="40605" author="vladimirwork" type="comment" body="INDY-2247 was reported for VC issues found in TestAuditSuite." created="2019-10-10 16:01:57.0" updateauthor="vladimirwork" updated="2019-10-10 16:01:57.0"/>
