<Action id="23334" issue="16122" author="denyeart" type="comment" created="2017-05-03 14:18:04.0" updateauthor="denyeart" updated="2017-05-03 14:18:04.0"> <body><! CDATA The block metadata contains the last config block location.  This can be used to directly navigate to the correct config block, rather than checking all the blocks.   ~kchristidis  Jeff mentioned you were making some changes to this metadata.  He suggested we connect before any fix is done here, to ensure you work is merged first.  Please add details/links.  Thanks.  ></body> </Action>
<Action id="23341" issue="16122" author="kchristidis" type="comment" created="2017-05-03 14:59:21.0" updateauthor="kchristidis" updated="2017-05-03 14:59:21.0"> <body><! CDATA  ~jeffgarratt  is right.  My LAST_CONFIG fix was merged earlier today so you should be good to go: https://gerrit.hyperledger.org/r/#/c/8825/  Let me know if you bump into any issues.  ></body> </Action>
<Action id="23631" issue="16122" author="denyeart" type="comment" body="https://gerrit.hyperledger.org/r/#/c/9185/" created="2017-05-10 12:24:25.0" updateauthor="denyeart" updated="2017-05-10 12:24:25.0"/>
<Action id="23633" issue="16122" author="yacovm" type="comment" body="I applied this patch locally on the server I discovered the problem on and it fixed the problem (the peer started right away)" created="2017-05-10 13:03:46.0" updateauthor="yacovm" updated="2017-05-10 13:04:20.0"/>
