<Action id="38746" issue="26303" author="gudkov" type="comment" created="2018-01-17 12:33:22.0" updateauthor="gudkov" updated="2018-01-17 12:33:22.0"> <body><! CDATA CLI and libindy always creates DID as part of verkey if possible. Allows CLI allows to input verkey in abbreviated form.  The only problem here is that we don't display verkeys as abbreviation.  Current vision is that we need to create helper method try_abbreviate_verkey(did, verkey) in CLI or libindy and use it in places when we display verkey with did together.  ></body> </Action>
<Action id="38841" issue="26303" author="artemkaaas" type="comment" body="Implemented in https://github.com/hyperledger/indy-sdk/pull/491" created="2018-01-18 13:53:05.0" updateauthor="artemkaaas" updated="2018-01-18 13:53:05.0"/>
<Action id="39016" issue="26303" author="artemkaaas" type="comment" created="2018-01-23 12:41:30.0" updateauthor="artemkaaas" updated="2018-01-23 12:41:30.0"> <body><! CDATA Changes:  -   Added indy_abbreviate_verkey API call to get abbreviated verkey form if it possible.  PR: *  https://github.com/hyperledger/indy-sdk/pull/491   Version: - master build #335  ></body> </Action>
<Action id="39236" issue="26303" author="zhigunenko.dsr" type="comment" created="2018-01-29 08:48:19.0" updateauthor="zhigunenko.dsr" updated="2018-01-29 08:58:45.0"> <body><! CDATA *Environment:* indy-node 1.2.282 indy-cli 1.3.0~337 libindy 1.3.0~337     *Steps to Validate:* # Create new DID and put it in the ledger. # Create DID with parametres. # rotate-key for DID.  *Actual Results:* 1. "did new" and "ledger get-nym did=" outputs show abbreviated verkey. 2. verkey shown but full 3. verkey shown but full  *Additional Information:*  Abbreviated verkey can be used only in case when DID creating without "did=" parameter. It's also always shown in pair "DID - verkey", not single. So cases 2 and 3 are allowable  ></body> </Action>
